README.md
nwb_schema_language-0.2.0.dist-info/METADATA
nwb_schema_language-0.2.0.dist-info/WHEEL
nwb_schema_language-0.2.0.dist-info/entry_points.txt
nwb_schema_language-0.2.0.dist-info/licenses/LICENSE
nwb_schema_language/.DS_Store
nwb_schema_language/__init__.py
nwb_schema_language/_version.py
nwb_schema_language/datamodel/__init__.py
nwb_schema_language/datamodel/nwb_schema_language.py
nwb_schema_language/datamodel/nwb_schema_pydantic.py
nwb_schema_language/datamodel/schemaview.py
nwb_schema_language/generator.py
nwb_schema_language/patches.py
nwb_schema_language/schema/nwb_schema_language.yaml
project/.DS_Store
project/docs/AnyType.md
project/docs/Attribute.md
project/docs/Attribute_name.md
project/docs/CompoundDtype.md
project/docs/CompoundDtype_dtype.md
project/docs/CompoundDtype_name.md
project/docs/Dataset.md
project/docs/DtypeMixin.md
project/docs/FlatDtype.md
project/docs/Group.md
project/docs/Link.md
project/docs/NamedThing.md
project/docs/Namespace_name.md
project/docs/Namespaces.md
project/docs/NamespacesCollection.md
project/docs/Namespaces_primary_email.md
project/docs/NamingMixin.md
project/docs/PersonStatus.md
project/docs/QuantityEnum.md
project/docs/ReferenceDtype.md
project/docs/Schema_doc.md
project/docs/age_in_years.md
project/docs/attributes.md
project/docs/author.md
project/docs/birth_date.md
project/docs/contact.md
project/docs/datasets.md
project/docs/date.md
project/docs/default_name.md
project/docs/default_value.md
project/docs/description.md
project/docs/dims.md
project/docs/doc.md
project/docs/dtype.md
project/docs/full_name.md
project/docs/groups.md
project/docs/id.md
project/docs/linkable.md
project/docs/links.md
project/docs/name.md
project/docs/namespace.md
project/docs/namespacesCollection__entries.md
project/docs/neurodata_type_def.md
project/docs/neurodata_type_inc.md
project/docs/neurodata_types.md
project/docs/nwb_schema_language.md
project/docs/primary_email.md
project/docs/quantity.md
project/docs/reftype.md
project/docs/reftype_options.md
project/docs/required.md
project/docs/schema.md
project/docs/schema__doc.md
project/docs/shape.md
project/docs/source.md
project/docs/target_type.md
project/docs/title.md
nwb_schema_language-0.2.0.dist-info/RECORD
