Metadata-Version: 2.1
Name: nwb-schema-language
Version: 0.2.0
Summary: Translation of the nwb-schema-language to LinkML
Home-page: https://nwb-linkml.readthedocs.io
Author-Email: Jonny Saunders <j@nny.fyi>
License: AGPL-3.0
Project-URL: Homepage, https://nwb-linkml.readthedocs.io
Project-URL: Repository, https://github.com/p2p-ld/nwb-linkml/
Project-URL: Documentation, https://nwb-linkml.readthedocs.io
Requires-Python: <3.13,>=3.10
Requires-Dist: linkml-runtime>=1.7.7
Requires-Dist: pydantic>=2.3.0
